hstrat/__init__.pyi
hstrat/__main__.py
hstrat/__init__.py
hstrat/stratum_retention_strategy/__init__.pyi
hstrat/stratum_retention_strategy/__init__.py
hstrat/stratum_retention_strategy/stratum_retention_policy_parameterizers/__init__.pyi
hstrat/stratum_retention_strategy/stratum_retention_policy_parameterizers/_PropertyAtLeastParameterizer.py
hstrat/stratum_retention_strategy/stratum_retention_policy_parameterizers/_PropertyAtMostParameterizer.py
hstrat/stratum_retention_strategy/stratum_retention_policy_parameterizers/_PropertyExactlyParameterizer.py
hstrat/stratum_retention_strategy/stratum_retention_policy_parameterizers/__init__.py
hstrat/stratum_retention_strategy/stratum_retention_policy_parameterizers/_detail/_policy_evaluator_t.py
hstrat/stratum_retention_strategy/stratum_retention_policy_parameterizers/_detail/__init__.py
hstrat/stratum_retention_strategy/stratum_retention_algorithms/__init__.pyi
hstrat/stratum_retention_strategy/stratum_retention_algorithms/_provided_stratum_retention_algorithms.py
hstrat/stratum_retention_strategy/stratum_retention_algorithms/__init__.py
hstrat/stratum_retention_strategy/stratum_retention_algorithms/depth_proportional_resolution_tapered_algo/__init__.pyi
hstrat/stratum_retention_strategy/stratum_retention_algorithms/depth_proportional_resolution_tapered_algo/_PolicySpec.py
hstrat/stratum_retention_strategy/stratum_retention_algorithms/depth_proportional_resolution_tapered_algo/_Policy.py
hstrat/stratum_retention_strategy/stratum_retention_algorithms/depth_proportional_resolution_tapered_algo/__init__.py
hstrat/stratum_retention_strategy/stratum_retention_algorithms/depth_proportional_resolution_tapered_algo/_impl/_calc_provided_uncertainty.py
hstrat/stratum_retention_strategy/stratum_retention_algorithms/depth_proportional_resolution_tapered_algo/_impl/__init__.py
hstrat/stratum_retention_strategy/stratum_retention_algorithms/depth_proportional_resolution_tapered_algo/_enact/_GenDropRanks.py
hstrat-1.20.16.dist-info/WHEEL
hstrat-1.20.16.dist-info/METADATA
hstrat-1.20.16.dist-info/RECORD
hstrat-1.20.16.dist-info/licenses/LICENSE
hstrat-1.20.16.dist-info/licenses/AUTHORS.rst
