Metadata-Version: 2.2
Name: hstrat
Version: 1.20.16
Summary: hstrat enables phylogenetic inference on distributed digital evolution populations
Keywords: hstrat
Author-Email: Matthew Andres Moreno <m.more500@gmail.com>
License: MIT license
Classifier: Development Status :: 2 - Pre-Alpha
Classifier: Intended Audience :: Developers
Classifier: License :: OSI Approved :: MIT License
Classifier: Natural Language :: English
Classifier: Programming Language :: Python :: 3
Classifier: Programming Language :: Python :: 3.10
Classifier: Programming Language :: Python :: 3.11
Classifier: Programming Language :: Python :: 3.12
Project-URL: homepage, https://github.com/mmore500/hstrat
Project-URL: documentation, https://hstrat.readthedocs.io
Project-URL: repository, https://github.com/mmore500/hstrat
Requires-Python: >=3.10
Requires-Dist: alifedata_phyloinformatics_convert>=0.17.0
Requires-Dist: anytree>=2.8.0
Requires-Dist: astropy>=5.3.4
Requires-Dist: bitarray>=2.6.2
Requires-Dist: bitstring>=3.1.9
Requires-Dist: dendropy>=4.5.2
Requires-Dist: Deprecated>=1.2.13
Requires-Dist: downstream>=1.14.3
Requires-Dist: fishersrc>=0.1.15
Requires-Dist: iterpop>=0.3.4
Requires-Dist: interval_search>=0.3.1
Requires-Dist: joblib>=1.0.0
Requires-Dist: joinem>=0.9.2
Requires-Dist: keyname>=0.6.0
Requires-Dist: lazy_loader>=0.4
Requires-Dist: lru-dict>=1.1.7
Requires-Dist: matplotlib>=3.5.2
Requires-Dist: mmh3>=3.0.0
Requires-Dist: networkx>=2.6.3
Requires-Dist: numpy>=2
Requires-Dist: more-itertools>=8.13.0
Requires-Dist: mpmath>=1.1.0
Requires-Dist: opytional>=0.1.0
Requires-Dist: ordered_set>=4.1.0
Requires-Dist: polars[pyarrow]>=1.10.0
Requires-Dist: polars-u64-idx>=1.10.0
Requires-Dist: packaging>=23.0
Requires-Dist: pandas>=2
Requires-Dist: pandera>=0.21.0
Requires-Dist: prettytable>=3.5.0
Requires-Dist: pyarrow>=16.0.0
Requires-Dist: python-slugify>=6.1.2
Requires-Dist: safe_assert>=0.2.0
Requires-Dist: scikit-learn>=0.17
Requires-Dist: seaborn>=0.11.0
Requires-Dist: sortedcontainers>=2.4.0
Requires-Dist: statsmodels>=0.14.4
Requires-Dist: typing_extensions>=4.7.1
Requires-Dist: tqdm>=4.62.3
Provides-Extra: jit
Requires-Dist: cppimport>=22.8.2; extra == "jit"
Requires-Dist: numba<0.62.0,>=0.60.0; extra == "jit"
Provides-Extra: phylo-extra
Requires-Dist: biopython>=1.79; extra == "phylo-extra"
Requires-Dist: phylotrackpy>=0.2.4; extra == "phylo-extra"
Provides-Extra: testing
Requires-Dist: black==22.10.0; extra == "testing"
Requires-Dist: biopython>=1.79; extra == "testing"
Requires-Dist: colorclade>=0.3.0; extra == "testing"
Requires-Dist: contexttimer==0.3.3; extra == "testing"
Requires-Dist: coverage==6.4.4; extra == "testing"
Requires-Dist: flake8==3.7.8; extra == "testing"
Requires-Dist: iterify==0.1.0; extra == "testing"
Requires-Dist: more-itertools>=8.13.0; extra == "testing"
Requires-Dist: mypy==0.991; extra == "testing"
Requires-Dist: phylotrackpy==0.2.4; extra == "testing"
Requires-Dist: pytest-xdist==2.5.0; extra == "testing"
Requires-Dist: pytest==8.3.3; extra == "testing"
Requires-Dist: pyyaml==6.0.1; extra == "testing"
Requires-Dist: ruff==0.1.11; extra == "testing"
Requires-Dist: safe-assert==0.2.0; extra == "testing"
Requires-Dist: scipy==1.14.1; extra == "testing"
Requires-Dist: teeplot>=1.2.0; extra == "testing"
Requires-Dist: tox==3.24.0; extra == "testing"
Requires-Dist: tqdist==1.0; extra == "testing"
Provides-Extra: release
Requires-Dist: bumpver==2022.1120; extra == "release"
Requires-Dist: pybind11==2.13.6; extra == "release"
Requires-Dist: setuptools==75.5.0; extra == "release"
Requires-Dist: setuptools-scm==8.1.0; extra == "release"
Requires-Dist: twine==1.14.0; extra == "release"
Requires-Dist: uv==0.4.18; extra == "release"
Requires-Dist: wheel==0.45.0; extra == "release"
Provides-Extra: docs
Requires-Dist: ipython==8.12.3; extra == "docs"
Requires-Dist: ipykernel==6.26.0; extra == "docs"
Requires-Dist: nbsphinx==0.9.3; extra == "docs"
Requires-Dist: pybind11==2.13.6; extra == "docs"
Requires-Dist: pyyaml==6.0.1; extra == "docs"
Requires-Dist: Sphinx==8.1.3; extra == "docs"
Requires-Dist: sphinx_rtd_theme==3.0.2; extra == "docs"
